odoo/addons/mass_mailing_contact_active/README.rst
odoo/addons/mass_mailing_contact_active/__init__.py
odoo/addons/mass_mailing_contact_active/__manifest__.py
odoo/addons/mass_mailing_contact_active/i18n/mass_mailing_contact_active.pot
odoo/addons/mass_mailing_contact_active/models/__init__.py
odoo/addons/mass_mailing_contact_active/models/mailing_contact.py
odoo/addons/mass_mailing_contact_active/models/mailing_contact_subscription.py
odoo/addons/mass_mailing_contact_active/readme/CONTRIBUTORS.rst
odoo/addons/mass_mailing_contact_active/readme/DESCRIPTION.rst
odoo/addons/mass_mailing_contact_active/static/description/icon.png
odoo/addons/mass_mailing_contact_active/static/description/index.html
odoo/addons/mass_mailing_contact_active/tests/__init__.py
odoo/addons/mass_mailing_contact_active/tests/test_mailing_contact_active.py
odoo13_addon_mass_mailing_contact_active-13.0.1.1.1.dev1.dist-info/METADATA
odoo13_addon_mass_mailing_contact_active-13.0.1.1.1.dev1.dist-info/WHEEL
odoo13_addon_mass_mailing_contact_active-13.0.1.1.1.dev1.dist-info/top_level.txt
odoo13_addon_mass_mailing_contact_active-13.0.1.1.1.dev1.dist-info/RECORD
